mkl_fft/__init__.py
mkl_fft/_fft_utils.py
mkl_fft/_init_helper.py
mkl_fft/_mkl_fft.py
mkl_fft/_pydfti.cp311-win_amd64.pyd
mkl_fft/_pydfti.pyx
mkl_fft/_version.py
mkl_fft/interfaces/__init__.py
mkl_fft/interfaces/_float_utils.py
mkl_fft/interfaces/_numpy_fft.py
mkl_fft/interfaces/_numpy_helper.py
mkl_fft/interfaces/_scipy_fft.py
mkl_fft/interfaces/numpy_fft.py
mkl_fft/interfaces/scipy_fft.py
mkl_fft/src/mklfft.c
mkl_fft/tests/__init__.py
mkl_fft/tests/helper.py
mkl_fft/tests/test_fft1d.py
mkl_fft/tests/test_fftnd.py
mkl_fft/tests/test_interfaces.py
mkl_fft/tests/third_party/numpy/test_fft.py
mkl_fft/tests/third_party/scipy/test_basic.py
mkl_fft/tests/third_party/scipy/test_multithreading.py
mkl_fft-2.1.2.dist-info/licenses/LICENSE.txt
mkl_fft-2.1.2.dist-info/METADATA
mkl_fft-2.1.2.dist-info/WHEEL
mkl_fft-2.1.2.dist-info/top_level.txt
mkl_fft-2.1.2.dist-info/RECORD
